{"relationshipsSections":[{"title":"Conforms To","type":"conformsTo","identifiers":["doc:\/\/com.mapbox.MapboxMaps\/documentation\/MapboxMaps\/Annotation","doc:\/\/com.mapbox.MapboxMaps\/documentation\/MapboxMaps\/MapContent","doc:\/\/com.mapbox.MapboxMaps\/s8CopyableP","doc:\/\/com.mapbox.MapboxMaps\/SQ"],"kind":"relationships"}],"seeAlsoSections":[{"identifiers":["doc:\/\/com.mapbox.MapboxMaps\/documentation\/MapboxMaps\/AnnotationOrchestrator","doc:\/\/com.mapbox.MapboxMaps\/documentation\/MapboxMaps\/AnnotationInteractionDelegate","doc:\/\/com.mapbox.MapboxMaps\/documentation\/MapboxMaps\/Annotation","doc:\/\/com.mapbox.MapboxMaps\/documentation\/MapboxMaps\/AnnotationManager","doc:\/\/com.mapbox.MapboxMaps\/documentation\/MapboxMaps\/CircleAnnotation","doc:\/\/com.mapbox.MapboxMaps\/documentation\/MapboxMaps\/CircleAnnotationManager","doc:\/\/com.mapbox.MapboxMaps\/documentation\/MapboxMaps\/PointAnnotation","doc:\/\/com.mapbox.MapboxMaps\/documentation\/MapboxMaps\/PointAnnotationManager","doc:\/\/com.mapbox.MapboxMaps\/documentation\/MapboxMaps\/PolygonAnnotation","doc:\/\/com.mapbox.MapboxMaps\/documentation\/MapboxMaps\/PolygonAnnotationManager","doc:\/\/com.mapbox.MapboxMaps\/documentation\/MapboxMaps\/PolylineAnnotationManager","doc:\/\/com.mapbox.MapboxMaps\/documentation\/MapboxMaps\/ClusterOptions"],"anchor":"Annotations","title":"Annotations","generated":true}],"primaryContentSections":[{"declarations":[{"languages":["swift"],"tokens":[{"text":"struct","kind":"keyword"},{"kind":"text","text":" "},{"text":"PolylineAnnotation","kind":"identifier"}],"platforms":["iOS"]}],"kind":"declarations"}],"hierarchy":{"paths":[["doc:\/\/com.mapbox.MapboxMaps\/documentation\/Overview","doc:\/\/com.mapbox.MapboxMaps\/documentation\/MapboxMaps","doc:\/\/com.mapbox.MapboxMaps\/documentation\/MapboxMaps\/Layer-Annotations"]]},"topicSections":[{"identifiers":["doc:\/\/com.mapbox.MapboxMaps\/documentation\/MapboxMaps\/PolylineAnnotation\/init(id:lineCoordinates:isSelected:isDraggable:)","doc:\/\/com.mapbox.MapboxMaps\/documentation\/MapboxMaps\/PolylineAnnotation\/init(id:lineString:isSelected:isDraggable:)"],"generated":true,"anchor":"Initializers","title":"Initializers"},{"anchor":"Instance-Properties","identifiers":["doc:\/\/com.mapbox.MapboxMaps\/documentation\/MapboxMaps\/PolylineAnnotation\/customData","doc:\/\/com.mapbox.MapboxMaps\/documentation\/MapboxMaps\/PolylineAnnotation\/dragBeginHandler","doc:\/\/com.mapbox.MapboxMaps\/documentation\/MapboxMaps\/PolylineAnnotation\/dragChangeHandler","doc:\/\/com.mapbox.MapboxMaps\/documentation\/MapboxMaps\/PolylineAnnotation\/dragEndHandler","doc:\/\/com.mapbox.MapboxMaps\/documentation\/MapboxMaps\/PolylineAnnotation\/geometry","doc:\/\/com.mapbox.MapboxMaps\/documentation\/MapboxMaps\/PolylineAnnotation\/id","doc:\/\/com.mapbox.MapboxMaps\/documentation\/MapboxMaps\/PolylineAnnotation\/isDraggable","doc:\/\/com.mapbox.MapboxMaps\/documentation\/MapboxMaps\/PolylineAnnotation\/isSelected","doc:\/\/com.mapbox.MapboxMaps\/documentation\/MapboxMaps\/PolylineAnnotation\/lineBlur","doc:\/\/com.mapbox.MapboxMaps\/documentation\/MapboxMaps\/PolylineAnnotation\/lineBorderColor","doc:\/\/com.mapbox.MapboxMaps\/documentation\/MapboxMaps\/PolylineAnnotation\/lineBorderWidth","doc:\/\/com.mapbox.MapboxMaps\/documentation\/MapboxMaps\/PolylineAnnotation\/lineColor","doc:\/\/com.mapbox.MapboxMaps\/documentation\/MapboxMaps\/PolylineAnnotation\/lineGapWidth","doc:\/\/com.mapbox.MapboxMaps\/documentation\/MapboxMaps\/PolylineAnnotation\/lineJoin","doc:\/\/com.mapbox.MapboxMaps\/documentation\/MapboxMaps\/PolylineAnnotation\/lineOffset","doc:\/\/com.mapbox.MapboxMaps\/documentation\/MapboxMaps\/PolylineAnnotation\/lineOpacity","doc:\/\/com.mapbox.MapboxMaps\/documentation\/MapboxMaps\/PolylineAnnotation\/linePattern","doc:\/\/com.mapbox.MapboxMaps\/documentation\/MapboxMaps\/PolylineAnnotation\/lineSortKey","doc:\/\/com.mapbox.MapboxMaps\/documentation\/MapboxMaps\/PolylineAnnotation\/lineString","doc:\/\/com.mapbox.MapboxMaps\/documentation\/MapboxMaps\/PolylineAnnotation\/lineWidth","doc:\/\/com.mapbox.MapboxMaps\/documentation\/MapboxMaps\/PolylineAnnotation\/lineZOffset","doc:\/\/com.mapbox.MapboxMaps\/documentation\/MapboxMaps\/PolylineAnnotation\/longPressHandler","doc:\/\/com.mapbox.MapboxMaps\/documentation\/MapboxMaps\/PolylineAnnotation\/tapHandler","doc:\/\/com.mapbox.MapboxMaps\/documentation\/MapboxMaps\/PolylineAnnotation\/userInfo"],"title":"Instance Properties","generated":true},{"identifiers":["doc:\/\/com.mapbox.MapboxMaps\/documentation\/MapboxMaps\/PolylineAnnotation\/lineBlur(_:)","doc:\/\/com.mapbox.MapboxMaps\/documentation\/MapboxMaps\/PolylineAnnotation\/lineBorderColor(_:)-1g9mw","doc:\/\/com.mapbox.MapboxMaps\/documentation\/MapboxMaps\/PolylineAnnotation\/lineBorderColor(_:)-3n2se","doc:\/\/com.mapbox.MapboxMaps\/documentation\/MapboxMaps\/PolylineAnnotation\/lineBorderWidth(_:)","doc:\/\/com.mapbox.MapboxMaps\/documentation\/MapboxMaps\/PolylineAnnotation\/lineColor(_:)-2f6cq","doc:\/\/com.mapbox.MapboxMaps\/documentation\/MapboxMaps\/PolylineAnnotation\/lineColor(_:)-7kowb","doc:\/\/com.mapbox.MapboxMaps\/documentation\/MapboxMaps\/PolylineAnnotation\/lineGapWidth(_:)","doc:\/\/com.mapbox.MapboxMaps\/documentation\/MapboxMaps\/PolylineAnnotation\/lineJoin(_:)","doc:\/\/com.mapbox.MapboxMaps\/documentation\/MapboxMaps\/PolylineAnnotation\/lineOffset(_:)","doc:\/\/com.mapbox.MapboxMaps\/documentation\/MapboxMaps\/PolylineAnnotation\/lineOpacity(_:)","doc:\/\/com.mapbox.MapboxMaps\/documentation\/MapboxMaps\/PolylineAnnotation\/linePattern(_:)","doc:\/\/com.mapbox.MapboxMaps\/documentation\/MapboxMaps\/PolylineAnnotation\/lineSortKey(_:)","doc:\/\/com.mapbox.MapboxMaps\/documentation\/MapboxMaps\/PolylineAnnotation\/lineWidth(_:)","doc:\/\/com.mapbox.MapboxMaps\/documentation\/MapboxMaps\/PolylineAnnotation\/lineZOffset(_:)","doc:\/\/com.mapbox.MapboxMaps\/documentation\/MapboxMaps\/PolylineAnnotation\/onLongPressGesture(handler:)-57x2d","doc:\/\/com.mapbox.MapboxMaps\/documentation\/MapboxMaps\/PolylineAnnotation\/onLongPressGesture(handler:)-8v9v9","doc:\/\/com.mapbox.MapboxMaps\/documentation\/MapboxMaps\/PolylineAnnotation\/onTapGesture(handler:)-2e24p","doc:\/\/com.mapbox.MapboxMaps\/documentation\/MapboxMaps\/PolylineAnnotation\/onTapGesture(handler:)-tfnm"],"title":"Instance Methods","generated":true,"anchor":"Instance-Methods"},{"title":"Default Implementations","generated":true,"identifiers":["doc:\/\/com.mapbox.MapboxMaps\/documentation\/MapboxMaps\/PolylineAnnotation\/Equatable-Implementations"],"anchor":"Default-Implementations"}],"identifier":{"url":"doc:\/\/com.mapbox.MapboxMaps\/documentation\/MapboxMaps\/PolylineAnnotation","interfaceLanguage":"swift"},"variants":[{"traits":[{"interfaceLanguage":"swift"}],"paths":["\/documentation\/mapboxmaps\/polylineannotation"]}],"schemaVersion":{"major":0,"patch":0,"minor":3},"kind":"symbol","sections":[],"metadata":{"symbolKind":"struct","title":"PolylineAnnotation","modules":[{"name":"MapboxMaps"}],"role":"symbol","fragments":[{"kind":"keyword","text":"struct"},{"kind":"text","text":" "},{"text":"PolylineAnnotation","kind":"identifier"}],"navigatorTitle":[{"text":"PolylineAnnotation","kind":"identifier"}],"roleHeading":"Structure","externalID":"s:10MapboxMaps18PolylineAnnotationV"},"references":{"doc://com.mapbox.MapboxMaps/documentation/MapboxMaps/PolylineAnnotation/lineOffset(_:)":{"role":"symbol","type":"topic","fragments":[{"kind":"keyword","text":"func"},{"text":" ","kind":"text"},{"text":"lineOffset","kind":"identifier"},{"text":"(","kind":"text"},{"text":"Double","kind":"typeIdentifier","preciseIdentifier":"s:Sd"},{"text":") -> ","kind":"text"},{"kind":"typeIdentifier","text":"PolylineAnnotation","preciseIdentifier":"s:10MapboxMaps18PolylineAnnotationV"}],"kind":"symbol","abstract":[{"text":"The line’s offset. For linear features, a positive value offsets the line to the right, relative to the direction of the line, and a negative value to the left. For polygon features, a positive value results in an inset, and a negative value results in an outset.","type":"text"},{"type":"text","text":" "},{"type":"text","text":"Default value: 0."}],"identifier":"doc:\/\/com.mapbox.MapboxMaps\/documentation\/MapboxMaps\/PolylineAnnotation\/lineOffset(_:)","title":"lineOffset(_:)","url":"\/documentation\/mapboxmaps\/polylineannotation\/lineoffset(_:)"},"doc://com.mapbox.MapboxMaps/documentation/MapboxMaps/PolylineAnnotation/lineWidth":{"fragments":[{"text":"var","kind":"keyword"},{"kind":"text","text":" "},{"text":"lineWidth","kind":"identifier"},{"text":": ","kind":"text"},{"preciseIdentifier":"s:Sd","kind":"typeIdentifier","text":"Double"},{"text":"?","kind":"text"}],"url":"\/documentation\/mapboxmaps\/polylineannotation\/linewidth","type":"topic","role":"symbol","title":"lineWidth","abstract":[{"text":"Stroke thickness.","type":"text"},{"text":" ","type":"text"},{"text":"Default value: 1. Minimum value: 0.","type":"text"}],"kind":"symbol","identifier":"doc:\/\/com.mapbox.MapboxMaps\/documentation\/MapboxMaps\/PolylineAnnotation\/lineWidth"},"doc://com.mapbox.MapboxMaps/documentation/MapboxMaps/PolylineAnnotation/lineString":{"abstract":[{"type":"text","text":"The LineString backing this annotation"}],"type":"topic","url":"\/documentation\/mapboxmaps\/polylineannotation\/linestring","role":"symbol","title":"lineString","fragments":[{"kind":"keyword","text":"var"},{"kind":"text","text":" "},{"text":"lineString","kind":"identifier"},{"kind":"text","text":": "},{"kind":"typeIdentifier","text":"LineString","preciseIdentifier":"s:4Turf10LineStringV"}],"identifier":"doc:\/\/com.mapbox.MapboxMaps\/documentation\/MapboxMaps\/PolylineAnnotation\/lineString","kind":"symbol"},"doc://com.mapbox.MapboxMaps/documentation/MapboxMaps/PolylineAnnotation/lineBorderWidth(_:)":{"abstract":[{"text":"The width of the line border. A value of zero means no border.","type":"text"},{"text":" ","type":"text"},{"text":"Default value: 0. Minimum value: 0.","type":"text"}],"url":"\/documentation\/mapboxmaps\/polylineannotation\/lineborderwidth(_:)","kind":"symbol","role":"symbol","title":"lineBorderWidth(_:)","fragments":[{"text":"func","kind":"keyword"},{"kind":"text","text":" "},{"text":"lineBorderWidth","kind":"identifier"},{"text":"(","kind":"text"},{"kind":"typeIdentifier","text":"Double","preciseIdentifier":"s:Sd"},{"text":") -> ","kind":"text"},{"preciseIdentifier":"s:10MapboxMaps18PolylineAnnotationV","text":"PolylineAnnotation","kind":"typeIdentifier"}],"identifier":"doc:\/\/com.mapbox.MapboxMaps\/documentation\/MapboxMaps\/PolylineAnnotation\/lineBorderWidth(_:)","type":"topic"},"doc://com.mapbox.MapboxMaps/documentation/MapboxMaps/PolylineAnnotation/userInfo":{"abstract":[{"text":"Properties associated with the annotation.","type":"text"}],"identifier":"doc:\/\/com.mapbox.MapboxMaps\/documentation\/MapboxMaps\/PolylineAnnotation\/userInfo","type":"topic","title":"userInfo","role":"symbol","kind":"symbol","url":"\/documentation\/mapboxmaps\/polylineannotation\/userinfo","fragments":[{"kind":"keyword","text":"var"},{"kind":"text","text":" "},{"text":"userInfo","kind":"identifier"},{"kind":"text","text":": ["},{"kind":"typeIdentifier","text":"String","preciseIdentifier":"s:SS"},{"text":" : ","kind":"text"},{"kind":"keyword","text":"Any"},{"kind":"text","text":"]?"}],"deprecated":true},"doc://com.mapbox.MapboxMaps/documentation/MapboxMaps/PolylineAnnotation":{"kind":"symbol","fragments":[{"kind":"keyword","text":"struct"},{"kind":"text","text":" "},{"text":"PolylineAnnotation","kind":"identifier"}],"type":"topic","role":"symbol","navigatorTitle":[{"kind":"identifier","text":"PolylineAnnotation"}],"title":"PolylineAnnotation","identifier":"doc:\/\/com.mapbox.MapboxMaps\/documentation\/MapboxMaps\/PolylineAnnotation","url":"\/documentation\/mapboxmaps\/polylineannotation","abstract":[]},"doc://com.mapbox.MapboxMaps/documentation/MapboxMaps/PolylineAnnotation/lineZOffset(_:)":{"fragments":[{"text":"func","kind":"keyword"},{"kind":"text","text":" "},{"text":"lineZOffset","kind":"identifier"},{"text":"(","kind":"text"},{"preciseIdentifier":"s:Sd","kind":"typeIdentifier","text":"Double"},{"text":") -> ","kind":"text"},{"text":"PolylineAnnotation","kind":"typeIdentifier","preciseIdentifier":"s:10MapboxMaps18PolylineAnnotationV"}],"url":"\/documentation\/mapboxmaps\/polylineannotation\/linezoffset(_:)","type":"topic","role":"symbol","title":"lineZOffset(_:)","abstract":[{"type":"text","text":"Vertical offset from ground, in meters. Defaults to 0. Not supported for globe projection at the moment."}],"kind":"symbol","identifier":"doc:\/\/com.mapbox.MapboxMaps\/documentation\/MapboxMaps\/PolylineAnnotation\/lineZOffset(_:)"},"doc://com.mapbox.MapboxMaps/documentation/MapboxMaps/PolylineAnnotation/lineColor(_:)-7kowb":{"abstract":[{"type":"text","text":"The color with which the line will be drawn."},{"text":" ","type":"text"},{"type":"text","text":"Default value: “#000000”."}],"url":"\/documentation\/mapboxmaps\/polylineannotation\/linecolor(_:)-7kowb","kind":"symbol","role":"symbol","title":"lineColor(_:)","fragments":[{"kind":"keyword","text":"func"},{"text":" ","kind":"text"},{"text":"lineColor","kind":"identifier"},{"kind":"text","text":"("},{"preciseIdentifier":"c:objc(cs)UIColor","text":"UIColor","kind":"typeIdentifier"},{"kind":"text","text":") -> "},{"preciseIdentifier":"s:10MapboxMaps18PolylineAnnotationV","text":"PolylineAnnotation","kind":"typeIdentifier"}],"identifier":"doc:\/\/com.mapbox.MapboxMaps\/documentation\/MapboxMaps\/PolylineAnnotation\/lineColor(_:)-7kowb","type":"topic"},"doc://com.mapbox.MapboxMaps/documentation/MapboxMaps/PolylineAnnotation/onTapGesture(handler:)-2e24p":{"abstract":[{"text":"Adds a handler for tap gesture on current annotation.","type":"text"}],"kind":"symbol","identifier":"doc:\/\/com.mapbox.MapboxMaps\/documentation\/MapboxMaps\/PolylineAnnotation\/onTapGesture(handler:)-2e24p","url":"\/documentation\/mapboxmaps\/polylineannotation\/ontapgesture(handler:)-2e24p","fragments":[{"text":"func","kind":"keyword"},{"text":" ","kind":"text"},{"text":"onTapGesture","kind":"identifier"},{"text":"(","kind":"text"},{"kind":"externalParam","text":"handler"},{"text":": (","kind":"text"},{"text":"InteractionContext","kind":"typeIdentifier","preciseIdentifier":"s:10MapboxMaps18InteractionContextV"},{"kind":"text","text":") -> "},{"text":"Bool","preciseIdentifier":"s:Sb","kind":"typeIdentifier"},{"text":") -> ","kind":"text"},{"text":"PolylineAnnotation","kind":"typeIdentifier","preciseIdentifier":"s:10MapboxMaps18PolylineAnnotationV"}],"role":"symbol","type":"topic","title":"onTapGesture(handler:)"},"doc://com.mapbox.MapboxMaps/documentation/MapboxMaps/AnnotationOrchestrator":{"kind":"symbol","navigatorTitle":[{"text":"AnnotationOrchestrator","kind":"identifier"}],"abstract":[{"code":"AnnotationOrchestrator","type":"codeVoice"},{"type":"text","text":" provides a way to create annotation managers of different types."}],"identifier":"doc:\/\/com.mapbox.MapboxMaps\/documentation\/MapboxMaps\/AnnotationOrchestrator","role":"symbol","url":"\/documentation\/mapboxmaps\/annotationorchestrator","fragments":[{"text":"class","kind":"keyword"},{"kind":"text","text":" "},{"text":"AnnotationOrchestrator","kind":"identifier"}],"title":"AnnotationOrchestrator","type":"topic"},"doc://com.mapbox.MapboxMaps/documentation/MapboxMaps/PolylineAnnotation/init(id:lineString:isSelected:isDraggable:)":{"kind":"symbol","type":"topic","role":"symbol","url":"\/documentation\/mapboxmaps\/polylineannotation\/init(id:linestring:isselected:isdraggable:)","abstract":[{"type":"text","text":"Create a polyline annotation with a "},{"code":"LineString","type":"codeVoice"},{"type":"text","text":" and an optional identifier."}],"title":"init(id:lineString:isSelected:isDraggable:)","identifier":"doc:\/\/com.mapbox.MapboxMaps\/documentation\/MapboxMaps\/PolylineAnnotation\/init(id:lineString:isSelected:isDraggable:)","fragments":[{"text":"init","kind":"identifier"},{"kind":"text","text":"("},{"kind":"externalParam","text":"id"},{"text":": ","kind":"text"},{"preciseIdentifier":"s:SS","text":"String","kind":"typeIdentifier"},{"kind":"text","text":", "},{"kind":"externalParam","text":"lineString"},{"kind":"text","text":": "},{"text":"LineString","kind":"typeIdentifier","preciseIdentifier":"s:4Turf10LineStringV"},{"text":", ","kind":"text"},{"text":"isSelected","kind":"externalParam"},{"kind":"text","text":": "},{"text":"Bool","preciseIdentifier":"s:Sb","kind":"typeIdentifier"},{"text":", ","kind":"text"},{"text":"isDraggable","kind":"externalParam"},{"text":": ","kind":"text"},{"kind":"typeIdentifier","text":"Bool","preciseIdentifier":"s:Sb"},{"text":")","kind":"text"}]},"doc://com.mapbox.MapboxMaps/documentation/MapboxMaps/PolylineAnnotation/linePattern(_:)":{"identifier":"doc:\/\/com.mapbox.MapboxMaps\/documentation\/MapboxMaps\/PolylineAnnotation\/linePattern(_:)","title":"linePattern(_:)","abstract":[{"type":"text","text":"Name of image in sprite to use for drawing image lines. For seamless patterns, image width must be a factor of two (2, 4, 8, …, 512). Note that zoom-dependent expressions will be evaluated only at integer zoom levels."}],"role":"symbol","type":"topic","fragments":[{"text":"func","kind":"keyword"},{"text":" ","kind":"text"},{"kind":"identifier","text":"linePattern"},{"text":"(","kind":"text"},{"kind":"typeIdentifier","preciseIdentifier":"s:SS","text":"String"},{"text":") -> ","kind":"text"},{"preciseIdentifier":"s:10MapboxMaps18PolylineAnnotationV","text":"PolylineAnnotation","kind":"typeIdentifier"}],"url":"\/documentation\/mapboxmaps\/polylineannotation\/linepattern(_:)","kind":"symbol"},"doc://com.mapbox.MapboxMaps/documentation/MapboxMaps/PolylineAnnotation/lineBorderColor(_:)-1g9mw":{"fragments":[{"text":"func","kind":"keyword"},{"kind":"text","text":" "},{"kind":"identifier","text":"lineBorderColor"},{"kind":"text","text":"("},{"kind":"typeIdentifier","preciseIdentifier":"s:10MapboxMaps10StyleColorV","text":"StyleColor"},{"text":") -> ","kind":"text"},{"text":"PolylineAnnotation","kind":"typeIdentifier","preciseIdentifier":"s:10MapboxMaps18PolylineAnnotationV"}],"kind":"symbol","identifier":"doc:\/\/com.mapbox.MapboxMaps\/documentation\/MapboxMaps\/PolylineAnnotation\/lineBorderColor(_:)-1g9mw","role":"symbol","type":"topic","abstract":[{"type":"text","text":"The color of the line border. If line-border-width is greater than zero and the alpha value of this color is 0 (default), the color for the border will be selected automatically based on the line color."},{"text":" ","type":"text"},{"type":"text","text":"Default value: “rgba(0, 0, 0, 0)”."}],"title":"lineBorderColor(_:)","url":"\/documentation\/mapboxmaps\/polylineannotation\/linebordercolor(_:)-1g9mw"},"doc://com.mapbox.MapboxMaps/documentation/MapboxMaps/PolylineAnnotation/longPressHandler":{"type":"topic","abstract":[{"type":"text","text":"Handles long press gesture on this annotation."}],"identifier":"doc:\/\/com.mapbox.MapboxMaps\/documentation\/MapboxMaps\/PolylineAnnotation\/longPressHandler","url":"\/documentation\/mapboxmaps\/polylineannotation\/longpresshandler","kind":"symbol","role":"symbol","fragments":[{"text":"var","kind":"keyword"},{"text":" ","kind":"text"},{"text":"longPressHandler","kind":"identifier"},{"text":": ((","kind":"text"},{"text":"InteractionContext","kind":"typeIdentifier","preciseIdentifier":"s:10MapboxMaps18InteractionContextV"},{"text":") -> ","kind":"text"},{"kind":"typeIdentifier","preciseIdentifier":"s:Sb","text":"Bool"},{"text":")?","kind":"text"}],"title":"longPressHandler"},"doc://com.mapbox.MapboxMaps/documentation/MapboxMaps/PolylineAnnotation/lineBorderColor":{"role":"symbol","identifier":"doc:\/\/com.mapbox.MapboxMaps\/documentation\/MapboxMaps\/PolylineAnnotation\/lineBorderColor","abstract":[{"text":"The color of the line border. If line-border-width is greater than zero and the alpha value of this color is 0 (default), the color for the border will be selected automatically based on the line color.","type":"text"},{"text":" ","type":"text"},{"type":"text","text":"Default value: “rgba(0, 0, 0, 0)”."}],"type":"topic","fragments":[{"kind":"keyword","text":"var"},{"text":" ","kind":"text"},{"text":"lineBorderColor","kind":"identifier"},{"kind":"text","text":": "},{"text":"StyleColor","kind":"typeIdentifier","preciseIdentifier":"s:10MapboxMaps10StyleColorV"},{"text":"?","kind":"text"}],"kind":"symbol","url":"\/documentation\/mapboxmaps\/polylineannotation\/linebordercolor","title":"lineBorderColor"},"doc://com.mapbox.MapboxMaps/documentation/MapboxMaps/PolylineAnnotation/tapHandler":{"abstract":[{"text":"Handles tap gesture on this annotation.","type":"text"}],"url":"\/documentation\/mapboxmaps\/polylineannotation\/taphandler","kind":"symbol","role":"symbol","title":"tapHandler","fragments":[{"text":"var","kind":"keyword"},{"kind":"text","text":" "},{"text":"tapHandler","kind":"identifier"},{"text":": ((","kind":"text"},{"kind":"typeIdentifier","text":"InteractionContext","preciseIdentifier":"s:10MapboxMaps18InteractionContextV"},{"text":") -> ","kind":"text"},{"kind":"typeIdentifier","text":"Bool","preciseIdentifier":"s:Sb"},{"text":")?","kind":"text"}],"identifier":"doc:\/\/com.mapbox.MapboxMaps\/documentation\/MapboxMaps\/PolylineAnnotation\/tapHandler","type":"topic"},"doc://com.mapbox.MapboxMaps/documentation/MapboxMaps/PolylineAnnotation/lineOpacity":{"abstract":[{"type":"text","text":"The opacity at which the line will be drawn."},{"type":"text","text":" "},{"text":"Default value: 1. Value range: [0, 1]","type":"text"}],"title":"lineOpacity","identifier":"doc:\/\/com.mapbox.MapboxMaps\/documentation\/MapboxMaps\/PolylineAnnotation\/lineOpacity","type":"topic","role":"symbol","kind":"symbol","url":"\/documentation\/mapboxmaps\/polylineannotation\/lineopacity","fragments":[{"kind":"keyword","text":"var"},{"text":" ","kind":"text"},{"text":"lineOpacity","kind":"identifier"},{"text":": ","kind":"text"},{"kind":"typeIdentifier","preciseIdentifier":"s:Sd","text":"Double"},{"text":"?","kind":"text"}]},"doc://com.mapbox.MapboxMaps/documentation/MapboxMaps/CircleAnnotationManager":{"kind":"symbol","abstract":[{"type":"text","text":"An instance of "},{"type":"codeVoice","code":"CircleAnnotationManager"},{"type":"text","text":" is responsible for a collection of "},{"code":"CircleAnnotation","type":"codeVoice"},{"text":"s.","type":"text"}],"fragments":[{"text":"class","kind":"keyword"},{"text":" ","kind":"text"},{"kind":"identifier","text":"CircleAnnotationManager"}],"title":"CircleAnnotationManager","role":"symbol","url":"\/documentation\/mapboxmaps\/circleannotationmanager","identifier":"doc:\/\/com.mapbox.MapboxMaps\/documentation\/MapboxMaps\/CircleAnnotationManager","navigatorTitle":[{"kind":"identifier","text":"CircleAnnotationManager"}],"type":"topic"},"doc://com.mapbox.MapboxMaps/documentation/MapboxMaps/AnnotationManager":{"role":"symbol","fragments":[{"kind":"keyword","text":"protocol"},{"text":" ","kind":"text"},{"kind":"identifier","text":"AnnotationManager"}],"navigatorTitle":[{"text":"AnnotationManager","kind":"identifier"}],"url":"\/documentation\/mapboxmaps\/annotationmanager","abstract":[],"title":"AnnotationManager","type":"topic","kind":"symbol","identifier":"doc:\/\/com.mapbox.MapboxMaps\/documentation\/MapboxMaps\/AnnotationManager"},"doc://com.mapbox.MapboxMaps/documentation/MapboxMaps/PolylineAnnotation/lineSortKey":{"url":"\/documentation\/mapboxmaps\/polylineannotation\/linesortkey","role":"symbol","type":"topic","abstract":[{"text":"Sorts features in ascending order based on this value. Features with a higher sort key will appear above features with a lower sort key.","type":"text"}],"kind":"symbol","title":"lineSortKey","identifier":"doc:\/\/com.mapbox.MapboxMaps\/documentation\/MapboxMaps\/PolylineAnnotation\/lineSortKey","fragments":[{"kind":"keyword","text":"var"},{"kind":"text","text":" "},{"kind":"identifier","text":"lineSortKey"},{"text":": ","kind":"text"},{"preciseIdentifier":"s:Sd","kind":"typeIdentifier","text":"Double"},{"kind":"text","text":"?"}]},"doc://com.mapbox.MapboxMaps/documentation/MapboxMaps/PolylineAnnotation/lineColor":{"fragments":[{"kind":"keyword","text":"var"},{"text":" ","kind":"text"},{"text":"lineColor","kind":"identifier"},{"kind":"text","text":": "},{"kind":"typeIdentifier","text":"StyleColor","preciseIdentifier":"s:10MapboxMaps10StyleColorV"},{"kind":"text","text":"?"}],"title":"lineColor","role":"symbol","url":"\/documentation\/mapboxmaps\/polylineannotation\/linecolor","kind":"symbol","type":"topic","identifier":"doc:\/\/com.mapbox.MapboxMaps\/documentation\/MapboxMaps\/PolylineAnnotation\/lineColor","abstract":[{"type":"text","text":"The color with which the line will be drawn."},{"text":" ","type":"text"},{"text":"Default value: “#000000”.","type":"text"}]},"doc://com.mapbox.MapboxMaps/documentation/MapboxMaps/PolylineAnnotation/dragEndHandler":{"title":"dragEndHandler","kind":"symbol","fragments":[{"text":"var","kind":"keyword"},{"kind":"text","text":" "},{"text":"dragEndHandler","kind":"identifier"},{"kind":"text","text":": (("},{"text":"inout","kind":"keyword"},{"kind":"text","text":" "},{"preciseIdentifier":"s:10MapboxMaps18PolylineAnnotationV","kind":"typeIdentifier","text":"PolylineAnnotation"},{"text":", ","kind":"text"},{"preciseIdentifier":"s:10MapboxMaps18InteractionContextV","text":"InteractionContext","kind":"typeIdentifier"},{"text":") -> ","kind":"text"},{"text":"Void","kind":"typeIdentifier","preciseIdentifier":"s:s4Voida"},{"text":")?","kind":"text"}],"type":"topic","identifier":"doc:\/\/com.mapbox.MapboxMaps\/documentation\/MapboxMaps\/PolylineAnnotation\/dragEndHandler","role":"symbol","abstract":[{"type":"text","text":"The handler receives the "},{"type":"codeVoice","code":"annotation"},{"text":" and the ","type":"text"},{"code":"context","type":"codeVoice"},{"type":"text","text":" parameters of the gesture:"}],"url":"\/documentation\/mapboxmaps\/polylineannotation\/dragendhandler"},"doc://com.mapbox.MapboxMaps/documentation/Overview":{"kind":"article","url":"\/documentation\/overview","title":"MapboxMaps Documentation","type":"topic","role":"collection","abstract":[],"identifier":"doc:\/\/com.mapbox.MapboxMaps\/documentation\/Overview"},"doc://com.mapbox.MapboxMaps/documentation/MapboxMaps/PolylineAnnotation/customData":{"kind":"symbol","type":"topic","role":"symbol","abstract":[{"text":"JSON convertible properties associated with the annotation, used to enrich Feature GeoJSON ","type":"text"},{"type":"codeVoice","code":"properties[\"custom_data\"]"},{"text":" field.","type":"text"}],"identifier":"doc:\/\/com.mapbox.MapboxMaps\/documentation\/MapboxMaps\/PolylineAnnotation\/customData","title":"customData","url":"\/documentation\/mapboxmaps\/polylineannotation\/customdata","fragments":[{"kind":"keyword","text":"var"},{"kind":"text","text":" "},{"text":"customData","kind":"identifier"},{"text":": ","kind":"text"},{"preciseIdentifier":"s:4Turf10JSONObjecta","kind":"typeIdentifier","text":"JSONObject"}]},"doc://com.mapbox.MapboxMaps/documentation/MapboxMaps/PolylineAnnotation/lineBorderColor(_:)-3n2se":{"role":"symbol","identifier":"doc:\/\/com.mapbox.MapboxMaps\/documentation\/MapboxMaps\/PolylineAnnotation\/lineBorderColor(_:)-3n2se","type":"topic","abstract":[{"type":"text","text":"The color of the line border. If line-border-width is greater than zero and the alpha value of this color is 0 (default), the color for the border will be selected automatically based on the line color."},{"text":" ","type":"text"},{"text":"Default value: “rgba(0, 0, 0, 0)”.","type":"text"}],"fragments":[{"kind":"keyword","text":"func"},{"text":" ","kind":"text"},{"text":"lineBorderColor","kind":"identifier"},{"kind":"text","text":"("},{"kind":"typeIdentifier","preciseIdentifier":"c:objc(cs)UIColor","text":"UIColor"},{"kind":"text","text":") -> "},{"text":"PolylineAnnotation","preciseIdentifier":"s:10MapboxMaps18PolylineAnnotationV","kind":"typeIdentifier"}],"kind":"symbol","url":"\/documentation\/mapboxmaps\/polylineannotation\/linebordercolor(_:)-3n2se","title":"lineBorderColor(_:)"},"doc://com.mapbox.MapboxMaps/documentation/MapboxMaps/PointAnnotation":{"identifier":"doc:\/\/com.mapbox.MapboxMaps\/documentation\/MapboxMaps\/PointAnnotation","abstract":[],"url":"\/documentation\/mapboxmaps\/pointannotation","type":"topic","role":"symbol","kind":"symbol","fragments":[{"text":"struct","kind":"keyword"},{"text":" ","kind":"text"},{"text":"PointAnnotation","kind":"identifier"}],"title":"PointAnnotation","navigatorTitle":[{"text":"PointAnnotation","kind":"identifier"}]},"doc://com.mapbox.MapboxMaps/documentation/MapboxMaps/PointAnnotationManager":{"url":"\/documentation\/mapboxmaps\/pointannotationmanager","role":"symbol","title":"PointAnnotationManager","abstract":[{"text":"An instance of ","type":"text"},{"type":"codeVoice","code":"PointAnnotationManager"},{"type":"text","text":" is responsible for a collection of "},{"type":"codeVoice","code":"PointAnnotation"},{"text":"s.","type":"text"}],"type":"topic","kind":"symbol","fragments":[{"kind":"keyword","text":"class"},{"kind":"text","text":" "},{"text":"PointAnnotationManager","kind":"identifier"}],"navigatorTitle":[{"kind":"identifier","text":"PointAnnotationManager"}],"identifier":"doc:\/\/com.mapbox.MapboxMaps\/documentation\/MapboxMaps\/PointAnnotationManager"},"doc://com.mapbox.MapboxMaps/documentation/MapboxMaps/PolylineAnnotation/id":{"role":"symbol","identifier":"doc:\/\/com.mapbox.MapboxMaps\/documentation\/MapboxMaps\/PolylineAnnotation\/id","abstract":[{"text":"Identifier for this annotation","type":"text"}],"type":"topic","fragments":[{"kind":"keyword","text":"var"},{"text":" ","kind":"text"},{"kind":"identifier","text":"id"},{"text":": ","kind":"text"},{"text":"String","kind":"typeIdentifier","preciseIdentifier":"s:SS"}],"kind":"symbol","url":"\/documentation\/mapboxmaps\/polylineannotation\/id","title":"id"},"doc://com.mapbox.MapboxMaps/documentation/MapboxMaps/PolylineAnnotation/onLongPressGesture(handler:)-8v9v9":{"abstract":[{"text":"Adds a handler for long press gesture on current annotation.","type":"text"}],"url":"\/documentation\/mapboxmaps\/polylineannotation\/onlongpressgesture(handler:)-8v9v9","kind":"symbol","role":"symbol","title":"onLongPressGesture(handler:)","fragments":[{"text":"func","kind":"keyword"},{"kind":"text","text":" "},{"text":"onLongPressGesture","kind":"identifier"},{"kind":"text","text":"("},{"text":"handler","kind":"externalParam"},{"kind":"text","text":": () -> "},{"text":"Void","kind":"typeIdentifier","preciseIdentifier":"s:s4Voida"},{"text":") -> ","kind":"text"},{"preciseIdentifier":"s:10MapboxMaps18PolylineAnnotationV","text":"PolylineAnnotation","kind":"typeIdentifier"}],"identifier":"doc:\/\/com.mapbox.MapboxMaps\/documentation\/MapboxMaps\/PolylineAnnotation\/onLongPressGesture(handler:)-8v9v9","type":"topic"},"doc://com.mapbox.MapboxMaps/documentation/MapboxMaps/PolylineAnnotation/lineBlur(_:)":{"title":"lineBlur(_:)","url":"\/documentation\/mapboxmaps\/polylineannotation\/lineblur(_:)","fragments":[{"text":"func","kind":"keyword"},{"kind":"text","text":" "},{"text":"lineBlur","kind":"identifier"},{"kind":"text","text":"("},{"text":"Double","kind":"typeIdentifier","preciseIdentifier":"s:Sd"},{"text":") -> ","kind":"text"},{"text":"PolylineAnnotation","preciseIdentifier":"s:10MapboxMaps18PolylineAnnotationV","kind":"typeIdentifier"}],"type":"topic","role":"symbol","identifier":"doc:\/\/com.mapbox.MapboxMaps\/documentation\/MapboxMaps\/PolylineAnnotation\/lineBlur(_:)","abstract":[{"type":"text","text":"Blur applied to the line, in pixels."},{"type":"text","text":" "},{"type":"text","text":"Default value: 0. Minimum value: 0."}],"kind":"symbol"},"doc://com.mapbox.MapboxMaps/documentation/MapboxMaps/PolylineAnnotation/lineWidth(_:)":{"fragments":[{"text":"func","kind":"keyword"},{"kind":"text","text":" "},{"text":"lineWidth","kind":"identifier"},{"kind":"text","text":"("},{"text":"Double","kind":"typeIdentifier","preciseIdentifier":"s:Sd"},{"kind":"text","text":") -> "},{"text":"PolylineAnnotation","preciseIdentifier":"s:10MapboxMaps18PolylineAnnotationV","kind":"typeIdentifier"}],"kind":"symbol","identifier":"doc:\/\/com.mapbox.MapboxMaps\/documentation\/MapboxMaps\/PolylineAnnotation\/lineWidth(_:)","role":"symbol","type":"topic","abstract":[{"type":"text","text":"Stroke thickness."},{"type":"text","text":" "},{"text":"Default value: 1. Minimum value: 0.","type":"text"}],"title":"lineWidth(_:)","url":"\/documentation\/mapboxmaps\/polylineannotation\/linewidth(_:)"},"doc://com.mapbox.MapboxMaps/documentation/MapboxMaps/PolylineAnnotation/lineGapWidth(_:)":{"role":"symbol","type":"topic","identifier":"doc:\/\/com.mapbox.MapboxMaps\/documentation\/MapboxMaps\/PolylineAnnotation\/lineGapWidth(_:)","abstract":[{"type":"text","text":"Draws a line casing outside of a line’s actual path. Value indicates the width of the inner gap."},{"type":"text","text":" "},{"type":"text","text":"Default value: 0. Minimum value: 0."}],"fragments":[{"kind":"keyword","text":"func"},{"kind":"text","text":" "},{"text":"lineGapWidth","kind":"identifier"},{"text":"(","kind":"text"},{"kind":"typeIdentifier","preciseIdentifier":"s:Sd","text":"Double"},{"kind":"text","text":") -> "},{"preciseIdentifier":"s:10MapboxMaps18PolylineAnnotationV","text":"PolylineAnnotation","kind":"typeIdentifier"}],"kind":"symbol","url":"\/documentation\/mapboxmaps\/polylineannotation\/linegapwidth(_:)","title":"lineGapWidth(_:)"},"doc://com.mapbox.MapboxMaps/documentation/MapboxMaps/ClusterOptions":{"kind":"symbol","navigatorTitle":[{"text":"ClusterOptions","kind":"identifier"}],"abstract":[{"text":"Options to configure point annotation clustering with PointAnnotationManager.","type":"text"}],"identifier":"doc:\/\/com.mapbox.MapboxMaps\/documentation\/MapboxMaps\/ClusterOptions","role":"symbol","url":"\/documentation\/mapboxmaps\/clusteroptions","fragments":[{"kind":"keyword","text":"struct"},{"kind":"text","text":" "},{"text":"ClusterOptions","kind":"identifier"}],"title":"ClusterOptions","type":"topic"},"doc://com.mapbox.MapboxMaps/documentation/MapboxMaps/PolylineAnnotation/Equatable-Implementations":{"type":"topic","abstract":[],"url":"\/documentation\/mapboxmaps\/polylineannotation\/equatable-implementations","kind":"article","title":"Equatable Implementations","role":"collectionGroup","identifier":"doc:\/\/com.mapbox.MapboxMaps\/documentation\/MapboxMaps\/PolylineAnnotation\/Equatable-Implementations"},"doc://com.mapbox.MapboxMaps/documentation/MapboxMaps/Map":{"navigatorTitle":[{"kind":"identifier","text":"Map"}],"identifier":"doc:\/\/com.mapbox.MapboxMaps\/documentation\/MapboxMaps\/Map","role":"symbol","title":"Map","abstract":[{"text":"A SwiftUI view that displays a Mapbox Map.","type":"text"}],"kind":"symbol","url":"\/documentation\/mapboxmaps\/map","fragments":[{"text":"struct","kind":"keyword"},{"kind":"text","text":" "},{"kind":"identifier","text":"Map"}],"type":"topic"},"doc://com.mapbox.MapboxMaps/documentation/MapboxMaps/MapContent":{"title":"MapContent","identifier":"doc:\/\/com.mapbox.MapboxMaps\/documentation\/MapboxMaps\/MapContent","navigatorTitle":[{"kind":"identifier","text":"MapContent"}],"type":"topic","fragments":[{"text":"protocol","kind":"keyword"},{"text":" ","kind":"text"},{"text":"MapContent","kind":"identifier"}],"role":"symbol","abstract":[{"type":"text","text":"A protocol used to create any type of "},{"identifier":"doc:\/\/com.mapbox.MapboxMaps\/documentation\/MapboxMaps\/Map","isActive":true,"type":"reference"},{"type":"text","text":" content, such as annotations, location indicator, layers, sources, lights, and more."}],"url":"\/documentation\/mapboxmaps\/mapcontent","kind":"symbol"},"doc://com.mapbox.MapboxMaps/documentation/MapboxMaps/PolylineAnnotationManager":{"url":"\/documentation\/mapboxmaps\/polylineannotationmanager","identifier":"doc:\/\/com.mapbox.MapboxMaps\/documentation\/MapboxMaps\/PolylineAnnotationManager","title":"PolylineAnnotationManager","role":"symbol","abstract":[{"text":"An instance of ","type":"text"},{"code":"PolylineAnnotationManager","type":"codeVoice"},{"text":" is responsible for a collection of ","type":"text"},{"type":"codeVoice","code":"PolylineAnnotation"},{"type":"text","text":"s."}],"type":"topic","navigatorTitle":[{"kind":"identifier","text":"PolylineAnnotationManager"}],"kind":"symbol","fragments":[{"text":"class","kind":"keyword"},{"kind":"text","text":" "},{"kind":"identifier","text":"PolylineAnnotationManager"}]},"doc://com.mapbox.MapboxMaps/documentation/MapboxMaps/PolylineAnnotation/lineColor(_:)-2f6cq":{"role":"symbol","identifier":"doc:\/\/com.mapbox.MapboxMaps\/documentation\/MapboxMaps\/PolylineAnnotation\/lineColor(_:)-2f6cq","fragments":[{"text":"func","kind":"keyword"},{"text":" ","kind":"text"},{"text":"lineColor","kind":"identifier"},{"text":"(","kind":"text"},{"preciseIdentifier":"s:10MapboxMaps10StyleColorV","text":"StyleColor","kind":"typeIdentifier"},{"kind":"text","text":") -> "},{"text":"PolylineAnnotation","preciseIdentifier":"s:10MapboxMaps18PolylineAnnotationV","kind":"typeIdentifier"}],"url":"\/documentation\/mapboxmaps\/polylineannotation\/linecolor(_:)-2f6cq","abstract":[{"text":"The color with which the line will be drawn.","type":"text"},{"type":"text","text":" "},{"type":"text","text":"Default value: “#000000”."}],"title":"lineColor(_:)","kind":"symbol","type":"topic"},"doc://com.mapbox.MapboxMaps/documentation/MapboxMaps/PolylineAnnotation/lineOffset":{"abstract":[{"type":"text","text":"The line’s offset. For linear features, a positive value offsets the line to the right, relative to the direction of the line, and a negative value to the left. For polygon features, a positive value results in an inset, and a negative value results in an outset."},{"type":"text","text":" "},{"text":"Default value: 0.","type":"text"}],"role":"symbol","kind":"symbol","fragments":[{"text":"var","kind":"keyword"},{"text":" ","kind":"text"},{"text":"lineOffset","kind":"identifier"},{"kind":"text","text":": "},{"kind":"typeIdentifier","preciseIdentifier":"s:Sd","text":"Double"},{"kind":"text","text":"?"}],"title":"lineOffset","url":"\/documentation\/mapboxmaps\/polylineannotation\/lineoffset","type":"topic","identifier":"doc:\/\/com.mapbox.MapboxMaps\/documentation\/MapboxMaps\/PolylineAnnotation\/lineOffset"},"doc://com.mapbox.MapboxMaps/documentation/MapboxMaps/PolylineAnnotation/lineZOffset":{"fragments":[{"text":"var","kind":"keyword"},{"kind":"text","text":" "},{"kind":"identifier","text":"lineZOffset"},{"kind":"text","text":": "},{"kind":"typeIdentifier","text":"Double","preciseIdentifier":"s:Sd"},{"text":"?","kind":"text"}],"title":"lineZOffset","kind":"symbol","abstract":[{"text":"Vertical offset from ground, in meters. Defaults to 0. Not supported for globe projection at the moment.","type":"text"}],"type":"topic","url":"\/documentation\/mapboxmaps\/polylineannotation\/linezoffset","identifier":"doc:\/\/com.mapbox.MapboxMaps\/documentation\/MapboxMaps\/PolylineAnnotation\/lineZOffset","role":"symbol"},"doc://com.mapbox.MapboxMaps/documentation/MapboxMaps/PolylineAnnotation/lineJoin(_:)":{"title":"lineJoin(_:)","identifier":"doc:\/\/com.mapbox.MapboxMaps\/documentation\/MapboxMaps\/PolylineAnnotation\/lineJoin(_:)","kind":"symbol","url":"\/documentation\/mapboxmaps\/polylineannotation\/linejoin(_:)","fragments":[{"kind":"keyword","text":"func"},{"text":" ","kind":"text"},{"kind":"identifier","text":"lineJoin"},{"text":"(","kind":"text"},{"text":"LineJoin","preciseIdentifier":"s:10MapboxMaps8LineJoinV","kind":"typeIdentifier"},{"text":") -> ","kind":"text"},{"kind":"typeIdentifier","preciseIdentifier":"s:10MapboxMaps18PolylineAnnotationV","text":"PolylineAnnotation"}],"abstract":[{"text":"The display of lines when joining.","type":"text"},{"type":"text","text":" "},{"text":"Default value: “miter”.","type":"text"}],"type":"topic","role":"symbol"},"doc://com.mapbox.MapboxMaps/documentation/MapboxMaps/Annotation":{"abstract":[{"type":"text","text":"A top-level interface for annotations."}],"kind":"symbol","fragments":[{"kind":"keyword","text":"protocol"},{"text":" ","kind":"text"},{"kind":"identifier","text":"Annotation"}],"title":"Annotation","role":"symbol","identifier":"doc:\/\/com.mapbox.MapboxMaps\/documentation\/MapboxMaps\/Annotation","url":"\/documentation\/mapboxmaps\/annotation","navigatorTitle":[{"text":"Annotation","kind":"identifier"}],"type":"topic"},"doc://com.mapbox.MapboxMaps/documentation/MapboxMaps/PolylineAnnotation/isDraggable":{"role":"symbol","type":"topic","abstract":[{"type":"text","text":"Property to determine whether annotation can be manually moved around map"}],"identifier":"doc:\/\/com.mapbox.MapboxMaps\/documentation\/MapboxMaps\/PolylineAnnotation\/isDraggable","fragments":[{"text":"var","kind":"keyword"},{"text":" ","kind":"text"},{"kind":"identifier","text":"isDraggable"},{"text":": ","kind":"text"},{"kind":"typeIdentifier","text":"Bool","preciseIdentifier":"s:Sb"}],"kind":"symbol","url":"\/documentation\/mapboxmaps\/polylineannotation\/isdraggable","title":"isDraggable"},"doc://com.mapbox.MapboxMaps/documentation/MapboxMaps/PolylineAnnotation/lineSortKey(_:)":{"kind":"symbol","type":"topic","role":"symbol","abstract":[{"text":"Sorts features in ascending order based on this value. Features with a higher sort key will appear above features with a lower sort key.","type":"text"}],"identifier":"doc:\/\/com.mapbox.MapboxMaps\/documentation\/MapboxMaps\/PolylineAnnotation\/lineSortKey(_:)","title":"lineSortKey(_:)","url":"\/documentation\/mapboxmaps\/polylineannotation\/linesortkey(_:)","fragments":[{"kind":"keyword","text":"func"},{"kind":"text","text":" "},{"kind":"identifier","text":"lineSortKey"},{"text":"(","kind":"text"},{"kind":"typeIdentifier","preciseIdentifier":"s:Sd","text":"Double"},{"text":") -> ","kind":"text"},{"preciseIdentifier":"s:10MapboxMaps18PolylineAnnotationV","text":"PolylineAnnotation","kind":"typeIdentifier"}]},"doc://com.mapbox.MapboxMaps/documentation/MapboxMaps/PolylineAnnotation/dragBeginHandler":{"kind":"symbol","abstract":[{"type":"text","text":"The handler is invoked when the user begins to drag the annotation."}],"type":"topic","url":"\/documentation\/mapboxmaps\/polylineannotation\/dragbeginhandler","role":"symbol","identifier":"doc:\/\/com.mapbox.MapboxMaps\/documentation\/MapboxMaps\/PolylineAnnotation\/dragBeginHandler","title":"dragBeginHandler","fragments":[{"kind":"keyword","text":"var"},{"kind":"text","text":" "},{"kind":"identifier","text":"dragBeginHandler"},{"text":": ((","kind":"text"},{"text":"inout","kind":"keyword"},{"text":" ","kind":"text"},{"kind":"typeIdentifier","preciseIdentifier":"s:10MapboxMaps18PolylineAnnotationV","text":"PolylineAnnotation"},{"kind":"text","text":", "},{"text":"InteractionContext","kind":"typeIdentifier","preciseIdentifier":"s:10MapboxMaps18InteractionContextV"},{"kind":"text","text":") -> "},{"kind":"typeIdentifier","preciseIdentifier":"s:Sb","text":"Bool"},{"text":")?","kind":"text"}]},"doc://com.mapbox.MapboxMaps/documentation/MapboxMaps":{"url":"\/documentation\/mapboxmaps","type":"topic","kind":"symbol","role":"collection","abstract":[{"type":"text","text":"Interactive, thoroughly customizable maps for iOS powered by vector tiles and Metal."}],"title":"MapboxMaps","identifier":"doc:\/\/com.mapbox.MapboxMaps\/documentation\/MapboxMaps"},"doc://com.mapbox.MapboxMaps/SQ":{"identifier":"doc:\/\/com.mapbox.MapboxMaps\/SQ","title":"Swift.Equatable","type":"unresolvable"},"doc://com.mapbox.MapboxMaps/documentation/MapboxMaps/PolylineAnnotation/lineBlur":{"fragments":[{"text":"var","kind":"keyword"},{"kind":"text","text":" "},{"kind":"identifier","text":"lineBlur"},{"kind":"text","text":": "},{"text":"Double","preciseIdentifier":"s:Sd","kind":"typeIdentifier"},{"text":"?","kind":"text"}],"kind":"symbol","role":"symbol","abstract":[{"text":"Blur applied to the line, in pixels.","type":"text"},{"text":" ","type":"text"},{"text":"Default value: 0. Minimum value: 0.","type":"text"}],"identifier":"doc:\/\/com.mapbox.MapboxMaps\/documentation\/MapboxMaps\/PolylineAnnotation\/lineBlur","type":"topic","title":"lineBlur","url":"\/documentation\/mapboxmaps\/polylineannotation\/lineblur"},"doc://com.mapbox.MapboxMaps/documentation/MapboxMaps/PolylineAnnotation/geometry":{"title":"geometry","url":"\/documentation\/mapboxmaps\/polylineannotation\/geometry","kind":"symbol","fragments":[{"text":"var","kind":"keyword"},{"text":" ","kind":"text"},{"kind":"identifier","text":"geometry"},{"kind":"text","text":": "},{"text":"Geometry","preciseIdentifier":"s:10MapboxMaps8Geometrya","kind":"typeIdentifier"}],"type":"topic","role":"symbol","abstract":[{"text":"The geometry backing this annotation","type":"text"}],"identifier":"doc:\/\/com.mapbox.MapboxMaps\/documentation\/MapboxMaps\/PolylineAnnotation\/geometry"},"doc://com.mapbox.MapboxMaps/documentation/MapboxMaps/PolygonAnnotation":{"navigatorTitle":[{"kind":"identifier","text":"PolygonAnnotation"}],"type":"topic","title":"PolygonAnnotation","kind":"symbol","url":"\/documentation\/mapboxmaps\/polygonannotation","fragments":[{"text":"struct","kind":"keyword"},{"kind":"text","text":" "},{"kind":"identifier","text":"PolygonAnnotation"}],"abstract":[],"identifier":"doc:\/\/com.mapbox.MapboxMaps\/documentation\/MapboxMaps\/PolygonAnnotation","role":"symbol"},"doc://com.mapbox.MapboxMaps/documentation/MapboxMaps/PolylineAnnotation/isSelected":{"type":"topic","url":"\/documentation\/mapboxmaps\/polylineannotation\/isselected","abstract":[{"text":"Toggles the annotation’s selection state.","type":"text"},{"type":"text","text":" "},{"type":"text","text":"If the annotation is deselected, it becomes selected."},{"type":"text","text":" "},{"text":"If the annotation is selected, it becomes deselected.","type":"text"}],"role":"symbol","kind":"symbol","title":"isSelected","fragments":[{"text":"var","kind":"keyword"},{"text":" ","kind":"text"},{"kind":"identifier","text":"isSelected"},{"kind":"text","text":": "},{"preciseIdentifier":"s:Sb","text":"Bool","kind":"typeIdentifier"}],"identifier":"doc:\/\/com.mapbox.MapboxMaps\/documentation\/MapboxMaps\/PolylineAnnotation\/isSelected"},"doc://com.mapbox.MapboxMaps/documentation/MapboxMaps/PolygonAnnotationManager":{"navigatorTitle":[{"kind":"identifier","text":"PolygonAnnotationManager"}],"role":"symbol","type":"topic","abstract":[{"text":"An instance of ","type":"text"},{"code":"PolygonAnnotationManager","type":"codeVoice"},{"type":"text","text":" is responsible for a collection of "},{"type":"codeVoice","code":"PolygonAnnotation"},{"type":"text","text":"s."}],"url":"\/documentation\/mapboxmaps\/polygonannotationmanager","kind":"symbol","identifier":"doc:\/\/com.mapbox.MapboxMaps\/documentation\/MapboxMaps\/PolygonAnnotationManager","fragments":[{"kind":"keyword","text":"class"},{"text":" ","kind":"text"},{"kind":"identifier","text":"PolygonAnnotationManager"}],"title":"PolygonAnnotationManager"},"doc://com.mapbox.MapboxMaps/documentation/MapboxMaps/Layer-Annotations":{"abstract":[],"type":"topic","url":"\/documentation\/mapboxmaps\/layer-annotations","title":"Layer Annotations","identifier":"doc:\/\/com.mapbox.MapboxMaps\/documentation\/MapboxMaps\/Layer-Annotations","kind":"article","role":"collectionGroup"},"doc://com.mapbox.MapboxMaps/documentation/MapboxMaps/PolylineAnnotation/init(id:lineCoordinates:isSelected:isDraggable:)":{"abstract":[{"text":"Create a polyline annotation with an array of coordinates and an optional identifier.","type":"text"}],"type":"topic","url":"\/documentation\/mapboxmaps\/polylineannotation\/init(id:linecoordinates:isselected:isdraggable:)","role":"symbol","title":"init(id:lineCoordinates:isSelected:isDraggable:)","fragments":[{"kind":"identifier","text":"init"},{"text":"(","kind":"text"},{"text":"id","kind":"externalParam"},{"text":": ","kind":"text"},{"text":"String","kind":"typeIdentifier","preciseIdentifier":"s:SS"},{"text":", ","kind":"text"},{"text":"lineCoordinates","kind":"externalParam"},{"text":": [","kind":"text"},{"text":"CLLocationCoordinate2D","preciseIdentifier":"c:@S@CLLocationCoordinate2D","kind":"typeIdentifier"},{"kind":"text","text":"], "},{"text":"isSelected","kind":"externalParam"},{"kind":"text","text":": "},{"kind":"typeIdentifier","preciseIdentifier":"s:Sb","text":"Bool"},{"kind":"text","text":", "},{"text":"isDraggable","kind":"externalParam"},{"text":": ","kind":"text"},{"preciseIdentifier":"s:Sb","text":"Bool","kind":"typeIdentifier"},{"text":")","kind":"text"}],"identifier":"doc:\/\/com.mapbox.MapboxMaps\/documentation\/MapboxMaps\/PolylineAnnotation\/init(id:lineCoordinates:isSelected:isDraggable:)","kind":"symbol"},"doc://com.mapbox.MapboxMaps/documentation/MapboxMaps/PolylineAnnotation/lineJoin":{"role":"symbol","type":"topic","abstract":[{"text":"The display of lines when joining.","type":"text"},{"text":" ","type":"text"},{"type":"text","text":"Default value: “miter”."}],"identifier":"doc:\/\/com.mapbox.MapboxMaps\/documentation\/MapboxMaps\/PolylineAnnotation\/lineJoin","fragments":[{"text":"var","kind":"keyword"},{"text":" ","kind":"text"},{"text":"lineJoin","kind":"identifier"},{"text":": ","kind":"text"},{"kind":"typeIdentifier","text":"LineJoin","preciseIdentifier":"s:10MapboxMaps8LineJoinV"},{"text":"?","kind":"text"}],"kind":"symbol","url":"\/documentation\/mapboxmaps\/polylineannotation\/linejoin","title":"lineJoin"},"doc://com.mapbox.MapboxMaps/documentation/MapboxMaps/PolylineAnnotation/linePattern":{"fragments":[{"kind":"keyword","text":"var"},{"kind":"text","text":" "},{"kind":"identifier","text":"linePattern"},{"text":": ","kind":"text"},{"kind":"typeIdentifier","preciseIdentifier":"s:SS","text":"String"},{"text":"?","kind":"text"}],"url":"\/documentation\/mapboxmaps\/polylineannotation\/linepattern","identifier":"doc:\/\/com.mapbox.MapboxMaps\/documentation\/MapboxMaps\/PolylineAnnotation\/linePattern","kind":"symbol","type":"topic","title":"linePattern","role":"symbol","abstract":[{"text":"Name of image in sprite to use for drawing image lines. For seamless patterns, image width must be a factor of two (2, 4, 8, …, 512). Note that zoom-dependent expressions will be evaluated only at integer zoom levels.","type":"text"}]},"doc://com.mapbox.MapboxMaps/documentation/MapboxMaps/PolylineAnnotation/onLongPressGesture(handler:)-57x2d":{"abstract":[{"type":"text","text":"Adds a handler for long press gesture on current annotation."}],"kind":"symbol","title":"onLongPressGesture(handler:)","fragments":[{"text":"func","kind":"keyword"},{"kind":"text","text":" "},{"kind":"identifier","text":"onLongPressGesture"},{"text":"(","kind":"text"},{"text":"handler","kind":"externalParam"},{"text":": (","kind":"text"},{"kind":"typeIdentifier","preciseIdentifier":"s:10MapboxMaps18InteractionContextV","text":"InteractionContext"},{"text":") -> ","kind":"text"},{"preciseIdentifier":"s:Sb","text":"Bool","kind":"typeIdentifier"},{"text":") -> ","kind":"text"},{"kind":"typeIdentifier","preciseIdentifier":"s:10MapboxMaps18PolylineAnnotationV","text":"PolylineAnnotation"}],"identifier":"doc:\/\/com.mapbox.MapboxMaps\/documentation\/MapboxMaps\/PolylineAnnotation\/onLongPressGesture(handler:)-57x2d","role":"symbol","url":"\/documentation\/mapboxmaps\/polylineannotation\/onlongpressgesture(handler:)-57x2d","type":"topic"},"doc://com.mapbox.MapboxMaps/documentation/MapboxMaps/AnnotationInteractionDelegate":{"role":"symbol","fragments":[{"text":"protocol","kind":"keyword"},{"kind":"text","text":" "},{"text":"AnnotationInteractionDelegate","kind":"identifier"}],"navigatorTitle":[{"kind":"identifier","text":"AnnotationInteractionDelegate"}],"url":"\/documentation\/mapboxmaps\/annotationinteractiondelegate","abstract":[{"type":"text","text":"A delegate that is called when a tap is detected on an annotation (or on several of them)."}],"title":"AnnotationInteractionDelegate","type":"topic","kind":"symbol","identifier":"doc:\/\/com.mapbox.MapboxMaps\/documentation\/MapboxMaps\/AnnotationInteractionDelegate"},"doc://com.mapbox.MapboxMaps/documentation/MapboxMaps/PolylineAnnotation/dragChangeHandler":{"kind":"symbol","role":"symbol","title":"dragChangeHandler","identifier":"doc:\/\/com.mapbox.MapboxMaps\/documentation\/MapboxMaps\/PolylineAnnotation\/dragChangeHandler","type":"topic","url":"\/documentation\/mapboxmaps\/polylineannotation\/dragchangehandler","abstract":[{"type":"text","text":"The handler is invoked when annotation is being dragged."}],"fragments":[{"kind":"keyword","text":"var"},{"text":" ","kind":"text"},{"text":"dragChangeHandler","kind":"identifier"},{"text":": ((","kind":"text"},{"text":"inout","kind":"keyword"},{"text":" ","kind":"text"},{"kind":"typeIdentifier","text":"PolylineAnnotation","preciseIdentifier":"s:10MapboxMaps18PolylineAnnotationV"},{"kind":"text","text":", "},{"text":"InteractionContext","kind":"typeIdentifier","preciseIdentifier":"s:10MapboxMaps18InteractionContextV"},{"text":") -> ","kind":"text"},{"text":"Void","kind":"typeIdentifier","preciseIdentifier":"s:s4Voida"},{"kind":"text","text":")?"}]},"doc://com.mapbox.MapboxMaps/documentation/MapboxMaps/PolylineAnnotation/lineGapWidth":{"abstract":[{"text":"Draws a line casing outside of a line’s actual path. Value indicates the width of the inner gap.","type":"text"},{"type":"text","text":" "},{"type":"text","text":"Default value: 0. Minimum value: 0."}],"title":"lineGapWidth","type":"topic","url":"\/documentation\/mapboxmaps\/polylineannotation\/linegapwidth","identifier":"doc:\/\/com.mapbox.MapboxMaps\/documentation\/MapboxMaps\/PolylineAnnotation\/lineGapWidth","kind":"symbol","role":"symbol","fragments":[{"text":"var","kind":"keyword"},{"text":" ","kind":"text"},{"text":"lineGapWidth","kind":"identifier"},{"kind":"text","text":": "},{"preciseIdentifier":"s:Sd","text":"Double","kind":"typeIdentifier"},{"kind":"text","text":"?"}]},"doc://com.mapbox.MapboxMaps/s8CopyableP":{"title":"Swift.Copyable","type":"unresolvable","identifier":"doc:\/\/com.mapbox.MapboxMaps\/s8CopyableP"},"doc://com.mapbox.MapboxMaps/documentation/MapboxMaps/PolylineAnnotation/onTapGesture(handler:)-tfnm":{"title":"onTapGesture(handler:)","identifier":"doc:\/\/com.mapbox.MapboxMaps\/documentation\/MapboxMaps\/PolylineAnnotation\/onTapGesture(handler:)-tfnm","abstract":[{"text":"Adds a handler for tap gesture on current annotation.","type":"text"}],"role":"symbol","type":"topic","fragments":[{"kind":"keyword","text":"func"},{"text":" ","kind":"text"},{"kind":"identifier","text":"onTapGesture"},{"text":"(","kind":"text"},{"text":"handler","kind":"externalParam"},{"kind":"text","text":": () -> "},{"text":"Void","preciseIdentifier":"s:s4Voida","kind":"typeIdentifier"},{"kind":"text","text":") -> "},{"text":"PolylineAnnotation","kind":"typeIdentifier","preciseIdentifier":"s:10MapboxMaps18PolylineAnnotationV"}],"url":"\/documentation\/mapboxmaps\/polylineannotation\/ontapgesture(handler:)-tfnm","kind":"symbol"},"doc://com.mapbox.MapboxMaps/documentation/MapboxMaps/PolylineAnnotation/lineBorderWidth":{"url":"\/documentation\/mapboxmaps\/polylineannotation\/lineborderwidth","fragments":[{"text":"var","kind":"keyword"},{"kind":"text","text":" "},{"text":"lineBorderWidth","kind":"identifier"},{"kind":"text","text":": "},{"preciseIdentifier":"s:Sd","text":"Double","kind":"typeIdentifier"},{"kind":"text","text":"?"}],"abstract":[{"text":"The width of the line border. A value of zero means no border.","type":"text"},{"type":"text","text":" "},{"text":"Default value: 0. Minimum value: 0.","type":"text"}],"type":"topic","identifier":"doc:\/\/com.mapbox.MapboxMaps\/documentation\/MapboxMaps\/PolylineAnnotation\/lineBorderWidth","kind":"symbol","title":"lineBorderWidth","role":"symbol"},"doc://com.mapbox.MapboxMaps/documentation/MapboxMaps/PolylineAnnotation/lineOpacity(_:)":{"kind":"symbol","identifier":"doc:\/\/com.mapbox.MapboxMaps\/documentation\/MapboxMaps\/PolylineAnnotation\/lineOpacity(_:)","url":"\/documentation\/mapboxmaps\/polylineannotation\/lineopacity(_:)","title":"lineOpacity(_:)","abstract":[{"type":"text","text":"The opacity at which the line will be drawn."},{"text":" ","type":"text"},{"type":"text","text":"Default value: 1. Value range: [0, 1]"}],"fragments":[{"kind":"keyword","text":"func"},{"kind":"text","text":" "},{"text":"lineOpacity","kind":"identifier"},{"text":"(","kind":"text"},{"text":"Double","kind":"typeIdentifier","preciseIdentifier":"s:Sd"},{"text":") -> ","kind":"text"},{"text":"PolylineAnnotation","kind":"typeIdentifier","preciseIdentifier":"s:10MapboxMaps18PolylineAnnotationV"}],"type":"topic","role":"symbol"},"doc://com.mapbox.MapboxMaps/documentation/MapboxMaps/CircleAnnotation":{"url":"\/documentation\/mapboxmaps\/circleannotation","role":"symbol","type":"topic","fragments":[{"kind":"keyword","text":"struct"},{"kind":"text","text":" "},{"text":"CircleAnnotation","kind":"identifier"}],"navigatorTitle":[{"kind":"identifier","text":"CircleAnnotation"}],"identifier":"doc:\/\/com.mapbox.MapboxMaps\/documentation\/MapboxMaps\/CircleAnnotation","abstract":[],"kind":"symbol","title":"CircleAnnotation"}}}